flask_sqlalchemy_lite/__init__.py
flask_sqlalchemy_lite/_cli.py
flask_sqlalchemy_lite/_extension.py
flask_sqlalchemy_lite/_make.py
flask_sqlalchemy_lite/py.typed
flask_sqlalchemy_lite-0.2.0.dist-info/licenses/LICENSE.txt
flask_sqlalchemy_lite-0.2.0.dist-info/WHEEL
flask_sqlalchemy_lite-0.2.0.dist-info/METADATA
flask_sqlalchemy_lite-0.2.0.dist-info/RECORD
