Metadata-Version: 2.4
Name: Flask-SQLAlchemy-Lite
Version: 0.2.0
Summary: Integrate SQLAlchemy with Flask.
Maintainer-email: Pallets <contact@palletsprojects.com>
Requires-Python: >=3.10
License-Expression: MIT
Classifier: Development Status :: 4 - Beta
Classifier: Framework :: Flask
Classifier: Programming Language :: Python
Classifier: Typing :: Typed
License-File: LICENSE.txt
Requires-Dist: flask[async]>=3.0.0
Requires-Dist: sqlalchemy[asyncio]>=2.0.31
Project-URL: Changes, https://flask-sqlalchemy-lite.readthedocs.io/page/changes/
Project-URL: Chat, https://discord.gg/pallets
Project-URL: Documentation, https://flask-sqlalchemy-lite.readthedocs.io
Project-URL: Donate, https://palletsprojects.com/donate
Project-URL: Source, https://github.com/pallets-eco/flask-sqlalchemy-lite/
